fixinventorydata/__init__.py
fixinventorydata/__main__.py
fixinventorydata/cloud.py
fixinventorydata/co2.py
fixinventorydata/colors.py
fixinventorydata/utils.py
fixinventorydata/data/ccfdataset.json
fixinventorydata/data/colors.json
fixinventorydata/data/instances.json
fixinventorydata/data/regions.json
fixinventorydata-0.2.6.dist-info/METADATA
fixinventorydata-0.2.6.dist-info/WHEEL
fixinventorydata-0.2.6.dist-info/entry_points.txt
fixinventorydata-0.2.6.dist-info/top_level.txt
fixinventorydata-0.2.6.dist-info/RECORD
