Metadata-Version: 2.1
Name: fixinventorydata
Version: 0.2.6
Summary: Miscellaneous Fix Inventory data.
License: Apache 2.0
Keywords: cloud security
Classifier: Development Status :: 4 - Beta
Classifier: Intended Audience :: System Administrators
Classifier: Intended Audience :: Information Technology
Classifier: License :: OSI Approved :: Apache Software License
Classifier: Programming Language :: Python :: 3.9
Classifier: Operating System :: POSIX :: Linux
Classifier: Operating System :: Unix
Classifier: Environment :: Console
Classifier: Natural Language :: English
Classifier: Topic :: Security
Classifier: Topic :: Utilities
Provides-Extra: dev
Requires-Dist: botocore ; extra == 'dev'
Requires-Dist: requests ; extra == 'dev'
Requires-Dist: geopy ; extra == 'dev'
Requires-Dist: beautifulsoup4 ; extra == 'dev'
